tensorflow_serving/__init__.py
tensorflow_serving/config/__init__.py
tensorflow_serving/config/file_system_storage_path_source_pb2.py
tensorflow_serving/config/log_collector_config_pb2.py
tensorflow_serving/config/logging_config_pb2.py
tensorflow_serving/config/model_server_config_pb2.py
tensorflow_serving/config/monitoring_config_pb2.py
tensorflow_serving/config/platform_config_pb2.py
tensorflow_serving/config/ssl_config_pb2.py
tensorflow_serving_config-0.0.2.dist-info/METADATA
tensorflow_serving_config-0.0.2.dist-info/WHEEL
tensorflow_serving_config-0.0.2.dist-info/top_level.txt
tensorflow_serving_config-0.0.2.dist-info/RECORD
