Metadata-Version: 2.1
Name: tensorflow-serving-config
Version: 0.0.2
Summary: Python utilities for reading, writing, and validating TensorFlow Serving models.config
Home-page: https://github.com/colorblank/tensorflow_serving_config
Author: Colorblank
Author-email: colorblank@example.com
License: Apache-2.0
Classifier: Programming Language :: Python :: 3
Classifier: License :: OSI Approved :: Apache Software License
Classifier: Operating System :: OS Independent
Requires-Python: >=3.9
Requires-Dist: grpcio>=1.64.1
Requires-Dist: protobuf>=4.25.3
